parselmouth.cpython-39-darwin.so
praat_parselmouth-0.4.6.dist-info/RECORD
praat_parselmouth-0.4.6.dist-info/WHEEL
praat_parselmouth-0.4.6.dist-info/top_level.txt
praat_parselmouth-0.4.6.dist-info/METADATA
praat_parselmouth-0.4.6.dist-info/licenses/LICENSE
