Metadata-Version: 2.1
Name: praat-parselmouth
Version: 0.4.6
Summary: Praat in Python, the Pythonic way
Home-page: https://github.com/YannickJadoul/Parselmouth
Author: Yannick Jadoul
Author-email: Yannick.Jadoul@ai.vub.ac.be
License: GPLv3
Project-URL: Source Code, https://github.com/YannickJadoul/Parselmouth
Project-URL: Bug Tracker, https://github.com/YannickJadoul/Parselmouth/issues
Project-URL: Documentation, https://parselmouth.readthedocs.io/
Keywords: praat,speech,signal processing,phonetics
Platform: UNKNOWN
Classifier: Development Status :: 5 - Production/Stable
Classifier: Intended Audience :: Developers
Classifier: Intended Audience :: Science/Research
Classifier: License :: OSI Approved :: GNU General Public License v3 or later (GPLv3+)
Classifier: Operating System :: MacOS :: MacOS X
Classifier: Operating System :: Microsoft :: Windows
Classifier: Operating System :: POSIX :: Linux
Classifier: Operating System :: Unix
Classifier: Programming Language :: C++
Classifier: Programming Language :: Python :: 2
Classifier: Programming Language :: Python :: 2.7
Classifier: Programming Language :: Python :: 3
Classifier: Programming Language :: Python :: 3.5
Classifier: Programming Language :: Python :: 3.6
Classifier: Programming Language :: Python :: 3.7
Classifier: Programming Language :: Python :: 3.8
Classifier: Programming Language :: Python :: 3.9
Classifier: Programming Language :: Python :: 3.10
Classifier: Programming Language :: Python :: 3.11
Classifier: Programming Language :: Python :: 3.12
Classifier: Topic :: Scientific/Engineering
Classifier: Topic :: Software Development :: Libraries :: Python Modules
Requires-Python: !=3.0.*,!=3.1.*,!=3.2.*,!=3.3.*,!=3.4.*,>=2.7
Requires-Dist: numpy (>=1.7.0)
